stabgraph/__init__.py
stabgraph/gauss_binary.py
stabgraph/stab_to_graph.py
stabgraph-0.1.2.dist-info/LICENSE.txt
stabgraph-0.1.2.dist-info/METADATA
stabgraph-0.1.2.dist-info/WHEEL
stabgraph-0.1.2.dist-info/top_level.txt
stabgraph-0.1.2.dist-info/RECORD
